ht/__init__.py
ht/air_cooler.py
ht/boiling_flow.py
ht/boiling_nucleic.py
ht/boiling_plate.py
ht/condensation.py
ht/conduction.py
ht/conv_external.py
ht/conv_free_enclosed.py
ht/conv_free_immersed.py
ht/conv_internal.py
ht/conv_jacket.py
ht/conv_packed_bed.py
ht/conv_plate.py
ht/conv_supercritical.py
ht/conv_tube_bank.py
ht/conv_two_phase.py
ht/core.py
ht/hx.py
ht/insulation.py
ht/numba.py
ht/numba_vectorized.py
ht/py.typed
ht/radiation.py
ht/units.py
ht/vectorized.py
ht/data/solar_iss_2018_spectrum.dat
ht/data/square_C1s_Phadkeb.npy
ht/data/square_Ns_Phadkeb.npy
ht/data/triangular_C1s_Phadkeb.npy
ht/data/triangular_Ns_Phadkeb.npy
ht-1.1.0.dist-info/licenses/AUTHORS
ht-1.1.0.dist-info/licenses/LICENSE.txt
ht-1.1.0.dist-info/METADATA
ht-1.1.0.dist-info/WHEEL
ht-1.1.0.dist-info/top_level.txt
ht-1.1.0.dist-info/RECORD
